odoo/addons/sale_payment_mode_brand/README.rst
odoo/addons/sale_payment_mode_brand/__init__.py
odoo/addons/sale_payment_mode_brand/__manifest__.py
odoo/addons/sale_payment_mode_brand/i18n/it.po
odoo/addons/sale_payment_mode_brand/i18n/sale_payment_mode_brand.pot
odoo/addons/sale_payment_mode_brand/readme/CONTRIBUTORS.md
odoo/addons/sale_payment_mode_brand/readme/DESCRIPTION.md
odoo/addons/sale_payment_mode_brand/readme/USAGE.md
odoo/addons/sale_payment_mode_brand/static/description/icon.png
odoo/addons/sale_payment_mode_brand/static/description/index.html
odoo/addons/sale_payment_mode_brand/views/sale_order.xml
odoo_addon_sale_payment_mode_brand-18.0.1.0.0.3.dist-info/METADATA
odoo_addon_sale_payment_mode_brand-18.0.1.0.0.3.dist-info/WHEEL
odoo_addon_sale_payment_mode_brand-18.0.1.0.0.3.dist-info/top_level.txt
odoo_addon_sale_payment_mode_brand-18.0.1.0.0.3.dist-info/RECORD
